Workbook

Sheet Base de donnes
A1: Country | B1: Name | C1: year | D1: Rule_of_law | E1: Return | F1: Volatility
A2: ECH | B2: iShares MSCI Chile ETF | C2: 2013 | D2: 0.69 | E2: =nav!H14 -> -0.24833712
A3: EDEN | B3: iShares MSCI Denmark ETF | C3: 2013 | D3: 0.88 | E3: =nav!H29 -> 0.41793681
A4: EFNL | B4: iShares MSCI Finland ETF | C4: 2013 | D4: 0.87 | E4: =nav!H43 -> 0.33954934
A5: EIDO | B5: iShares MSCI Indonesia ETF | C5: 2013 | D5: 0.52 | E5: =nav!H56 -> 0.22327451
A6: ENOR | B6: iShares MSCI Norway ETF | C6: 2013 | D6: 0.87 | E6: =nav!H71 -> 0.076305346
A7: ENZL | B7: iShares MSCI New Zealand ETF | C7: 2013 | D7: 0.84 | E7: =nav!H85 -> 0.092000571
A8: EPHE | B8: iShares MSCI Philippines ETF | C8: 2013 | D8: 0.49 | E8: =nav!H99 -> -0.088131237
A9: EPOL | B9: iShares MSCI Poland ETF | C9: 2013 | D9: 0.72 | E9: =nav!H113 -> 0.010530099
A10: EWA | B10: iShares MSCI Australia ETF | C10: 2013 | D10: 0.83 | E10: =nav!H126 -> -0.082034671
A11: EWC | B11: iShares MSCI Canada ETF | C11: 2013 | D11: 0.79 | E11: =nav!H141 -> 0.02821044
A12: EWD | B12: iShares MSCI Sweden ETF | C12: 2013 | D12: 0.89 | E12: =nav!H155 -> 0.19754171
A13: EWG | B13: iShares MSCI Germany ETF | C13: 2013 | D13: 0.79 | E13: =nav!H169 -> 0.28896933
A14: EWH | B14: iShares MSCI Hong Kong ETF | C14: 2013 | D14: 0.79 | E14: =nav!H183 -> 0.069589903
A15: EWI | B15: iShares MSCI Italy ETF | C15: 2013 | D15: 0.63 | E15: =nav!H197 -> 0.17706229
A16: EWJ | B16: iShares MSCI Japan ETF | C16: 2013 | D16: 0.81 | E16: =nav!H211 -> 0.2490366
A17: EWK | B17: iShares MSCI Belgium ETF | C17: 2013 | D17: 0.75 | E17: =nav!H225 -> 0.19816599
A18: EWM | B18: iShares MSCI Malaysia ETF | C18: 2013 | D18: 0.6 | E18: =nav!H239 -> 0.038155713
A19: EWO | B19: iShares MSCI Austria ETF | C19: 2013 | D19: 0.81 | E19: =nav!H253 -> 0.10627149
A20: EWP | B20: iShares MSCI Spain ETF | C20: 2013 | D20: 0.73 | E20: =nav!H267 -> 0.29775257
A21: EWQ | B21: iShares MSCI France ETF | C21: 2013 | D21: 0.76 | E21: =nav!H281 -> 0.22813853
A22: EWS | B22: iShares MSCI Singapore ETF | C22: 2013 | D22: 0.8 | E22: =nav!H295 -> -0.028773171
A23: EWU | B23: iShares MSCI United Kingdom ETF | C23: 2013 | D23: 0.78 | E23: =nav!H309 -> 0.16863613
A24: EWW | B24: iShares MSCI Mexico ETF | C24: 2013 | D24: 0.47 | E24: =nav!H323 -> -0.034460191
A25: EWY | B25: iShares MSCI South Korea ETF | C25: 2013 | D25: 0.73 | E25: =nav!H337 -> 0.020133572
A26: EWZ | B26: iShares MSCI Brazil ETF | C26: 2013 | D26: 0.58 | E26: =nav!H351 -> -0.19643894
A27: EZA | B27: iShares MSCI South Africa ETF | C27: 2013 | D27: 0.56 | E27: =nav!H365 -> -0.092509547
A28: INDA | B28: iShares MSCI India ETF | C28: 2013 | D28: 0.46 | E28: =nav!H379 -> -0.048710592
A29: MCHI | B29: iShares MSCI China ETF | C29: 2013 | D29: 0.48 | E29: =nav!H393 -> 0.0034138387
A30: THD | B30: iShares MSCI Thailand ETF | C30: 2013 | D30: 0.53 | E30: =nav!H407 -> -0.1718159
A31: TUR | B31: iShares MSCI Turkey ETF | C31: 2013 | D31: 0.52 | E31: =nav!H421 -> -0.28125786
A32: ECH | B32: iShares MSCI Chile ETF | C32: 2014 | D32: 0.68 | E32: =nav!H13 -> -0.14054933
A33: EDEN | B33: iShares MSCI Denmark ETF | C33: 2014 | D33: 0.88 | E33: =nav!H28 -> 0.058331877
A34: EFNL | B34: iShares MSCI Finland ETF | C34: 2014 | D34: 0.84 | E34: =nav!H42 -> -0.06699536
A35: EIDO | B35: iShares MSCI Indonesia ETF | C35: 2014 | D35: 0.52 | E35: =nav!H56 -> 0.22327451
A36: ENOR | B36: iShares MSCI Norway ETF | C36: 2014 | D36: 0.88 | E36: =nav!H70 -> -0.24841556
A37: ENZL | B37: iShares MSCI New Zealand ETF | C37: 2014 | D37: 0.83 | E37: =nav!H84 -> 0.074632963
A38: EPHE | B38: iShares MSCI Philippines ETF | C38: 2014 | D38: 0.5 | E38: =nav!H98 -> 0.23943981
A39: EPOL | B39: iShares MSCI Poland ETF | C39: 2014 | D39: 0.67 | E39: =nav!H112 -> -0.17964267
A40: EWA | B40: iShares MSCI Australia ETF | C40: 2014 | D40: 0.8 | E40: =nav!H126 -> -0.082034671
A41: EWC | B41: iShares MSCI Canada ETF | C41: 2014 | D41: 0.78 | E41: =nav!H140 -> -0.0077877216
A42: EWD | B42: iShares MSCI Sweden ETF | C42: 2014 | D42: 0.85 | E42: =nav!H154 -> -0.1068939
A43: EWG | B43: iShares MSCI Germany ETF | C43: 2014 | D43: 0.8 | E43: =nav!H168 -> -0.12264552
A44: EWH | B44: iShares MSCI Hong Kong ETF | C44: 2014 | D44: 0.76 | E44: =nav!H182 -> 0.0097853797
A45: EWI | B45: iShares MSCI Italy ETF | C45: 2014 | D45: 0.63 | E45: =nav!H196 -> -0.11666947
A46: EWJ | B46: iShares MSCI Japan ETF | C46: 2014 | D46: 0.78 | E46: =nav!H210 -> -0.056421699
A47: EWK | B47: iShares MSCI Belgium ETF | C47: 2014 | D47: 0.76 | E47: =nav!H224 -> 0.00014239609
A48: EWM | B48: iShares MSCI Malaysia ETF | C48: 2014 | D48: 0.58 | E48: =nav!H238 -> -0.13915581
A49: EWO | B49: iShares MSCI Austria ETF | C49: 2014 | D49: 0.82 | E49: =nav!H252 -> -0.22572605
A50: EWP | B50: iShares MSCI Spain ETF | C50: 2014 | D50: 0.67 | E50: =nav!H266 -> -0.087125443
A51: EWQ | B51: iShares MSCI France ETF | C51: 2014 | D51: 0.74 | E51: =nav!H280 -> -0.12548467
A52: EWS | B52: iShares MSCI Singapore ETF | C52: 2014 | D52: 0.79 | E52: =nav!H294 -> -0.0045102872
A53: EWU | B53: iShares MSCI United Kingdom ETF | C53: 2014 | D53: 0.78 | E53: =nav!H308 -> -0.1206436
A54: EWW | B54: iShares MSCI Mexico ETF | C54: 2014 | D54: 0.45 | E54: =nav!H322 -> -0.11235639
A55: EWY | B55: iShares MSCI South Korea ETF | C55: 2014 | D55: 0.77 | E55: =nav!H336 -> -0.129573
A56: EWZ | B56: iShares MSCI Brazil ETF | C56: 2014 | D56: 0.54 | E56: =nav!H350 -> -0.1717227
A57: EZA | B57: iShares MSCI South Africa ETF | C57: 2014 | D57: 0.55 | E57: =nav!H364 -> 0.022650066
A58: INDA | B58: iShares MSCI India ETF | C58: 2014 | D58: 0.48 | E58: =nav!H378 -> 0.22537741
A59: MCHI | B59: iShares MSCI China ETF | C59: 2014 | D59: 0.45 | E59: =nav!H392 -> 0.047815371
A60: THD | B60: iShares MSCI Thailand ETF | C60: 2014 | D60: 0.52 | E60: =nav!H406 -> 0.1526531
A61: TUR | B61: iShares MSCI Turkey ETF | C61: 2014 | D61: 0.5 | E61: =nav!H420 -> 0.14899015
A62: ECH | B62: iShares MSCI Chile ETF | C62: 2015 | D62: 0.69 | E62: =nav!H12 -> -0.19505471
A63: EDEN | B63: iShares MSCI Denmark ETF | C63: 2015 | D63: 0.89 | E63: =nav!H27 -> 0.19257294
A64: EFNL | B64: iShares MSCI Finland ETF | C64: 2015 | D64: 0.87 | E64: =nav!H41 -> 0.026732981
A65: EIDO | B65: iShares MSCI Indonesia ETF | C65: 2015 | D65: 0.51 | E65: =nav!H55 -> -0.23180838
A66: ENOR | B66: iShares MSCI Norway ETF | C66: 2015 | D66: 0.88 | E66: =nav!H69 -> -0.18049854
A67: ENZL | B67: iShares MSCI New Zealand ETF | C67: 2015 | D67: 0.84 | E67: =nav!H83 -> -0.055798632
A68: EPHE | B68: iShares MSCI Philippines ETF | C68: 2015 | D68: 0.52 | E68: =nav!H97 -> -0.11267504
A69: EPOL | B69: iShares MSCI Poland ETF | C69: 2015 | D69: 0.72 | E69: =nav!H111 -> -0.24970999
A70: EWA | B70: iShares MSCI Australia ETF | C70: 2015 | D70: 0.81 | E70: =nav!H125 -> -0.14816535
A71: EWC | B71: iShares MSCI Canada ETF | C71: 2015 | D71: 0.79 | E71: =nav!H139 -> -0.25878115
A72: EWD | B72: iShares MSCI Sweden ETF | C72: 2015 | D72: 0.87 | E72: =nav!H153 -> -0.070543919
A73: EWG | B73: iShares MSCI Germany ETF | C73: 2015 | D73: 0.83 | E73: =nav!H167 -> -0.037391151
A74: EWH | B74: iShares MSCI Hong Kong ETF | C74: 2015 | D74: 0.77 | E74: =nav!H181 -> -0.037598339
A75: EWI | B75: iShares MSCI Italy ETF | C75: 2015 | D75: 0.65 | E75: =nav!H195 -> 0.018633716
A76: EWJ | B76: iShares MSCI Japan ETF | C76: 2015 | D76: 0.79 | E76: =nav!H209 -> 0.080272118
A77: EWK | B77: iShares MSCI Belgium ETF | C77: 2015 | D77: 0.78 | E77: =nav!H223 -> 0.11088478
A78: EWM | B78: iShares MSCI Malaysia ETF | C78: 2015 | D78: 0.55 | E78: =nav!H237 -> -0.42533776
A79: EWO | B79: iShares MSCI Austria ETF | C79: 2015 | D79: 0.83 | E79: =nav!H251 -> 0.034188576
A80: EWP | B80: iShares MSCI Spain ETF | C80: 2015 | D80: 0.7 | E80: =nav!H265 -> -0.18702862
A81: EWQ | B81: iShares MSCI France ETF | C81: 2015 | D81: 0.75 | E81: =nav!H279 -> -0.021765417
A82: EWS | B82: iShares MSCI Singapore ETF | C82: 2015 | D82: 0.82 | E82: =nav!H293 -> -0.21031219
A83: EWU | B83: iShares MSCI United Kingdom ETF | C83: 2015 | D83: 0.8 | E83: =nav!H307 -> -0.11417753
A84: EWW | B84: iShares MSCI Mexico ETF | C84: 2015 | D84: 0.48 | E84: =nav!H321 -> -0.16133228
A85: EWY | B85: iShares MSCI South Korea ETF | C85: 2015 | D85: 0.79 | E85: =nav!H335 -> -0.089099754
A86: EWZ | B86: iShares MSCI Brazil ETF | C86: 2015 | D86: 0.55 | E86: =nav!H349 -> -0.42997686
A87: EZA | B87: iShares MSCI South Africa ETF | C87: 2015 | D87: 0.58 | E87: =nav!H363 -> -0.27828437
A88: INDA | B88: iShares MSCI India ETF | C88: 2015 | D88: 0.51 | E88: =nav!H377 -> -0.077023241
A89: MCHI | B89: iShares MSCI China ETF | C89: 2015 | D89: 0.48 | E89: =nav!H391 -> -0.10450285
A90: THD | B90: iShares MSCI Thailand ETF | C90: 2015 | D90: 0.52 | E90: =nav!H405 -> -0.23436083
A91: TUR | B91: iShares MSCI Turkey ETF | C91: 2015 | D91: 0.46 | E91: =nav!H419 -> -0.33061093
A92: ECH | B92: iShares MSCI Chile ETF | C92: 2016 | D92: 0.69 | E92: =nav!H11 -> 0.1558441
A93: EDEN | B93: iShares MSCI Denmark ETF | C93: 2016 | D93: 0.89 | E93: =nav!H26 -> -0.091134862
A94: EFNL | B94: iShares MSCI Finland ETF | C94: 2016 | D94: 0.88 | E94: =nav!H40 -> 0.0012110203
A95: EIDO | B95: iShares MSCI Indonesia ETF | C95: 2016 | D95: 0.52 | E95: =nav!H54 -> 0.15457248
A96: ENOR | B96: iShares MSCI Norway ETF | C96: 2016 | D96: 0.88 | E96: =nav!H68 -> 0.14225011
A97: ENZL | B97: iShares MSCI New Zealand ETF | C97: 2016 | D97: 0.83 | E97: =nav!H82 -> 0.059543173
A98: EPHE | B98: iShares MSCI Philippines ETF | C98: 2016 | D98: 0.51 | E98: =nav!H96 -> -0.057962152
A99: EPOL | B99: iShares MSCI Poland ETF | C99: 2016 | D99: 0.72 | E99: =nav!H110 -> 0.005515177
A100: EWA | B100: iShares MSCI Australia ETF | C100: 2016 | D100: 0.81 | E100: =nav!H124 -> 0.06630291
...

Sheet nav
A1: Country | B1: Name | C1: Date | D1: NAV por acción | E1: Dividedndos excluidos | F1: Shares Outstanding | G1: Non-FV NAV | H1: Return | I1: Volatility
A2: ECH | B2: iShares MSCI Chile ETF | C2: 12-31-2025 | D2: 40.496585 | E2: -- | F2: 25550000 | H2: =(D2-D3)/D3 -> 0.60740001
A3: ECH | B3: iShares MSCI Chile ETF | C3: 12-31-2024 | D3: 25.193844 | E3: -- | F3: 18950000 | H3: =(D3-D4)/D4 -> -0.10458879
A4: ECH | B4: iShares MSCI Chile ETF | C4: 12-29-2023 | D4: 28.136619 | E4: -- | F4: 22300000 | H4: =(D4-D5)/D5 -> 0.045848731
A5: ECH | B5: iShares MSCI Chile ETF | C5: 12-30-2022 | D5: 26.903144 | E5: -- | F5: 19200000 | H5: =(D5-D6)/D6 -> 0.1623168
A6: ECH | B6: iShares MSCI Chile ETF | C6: 12-31-2021 | D6: 23.146137 | E6: -- | F6: 18350000 | H6: =(D6-D7)/D7 -> -0.23206125
A7: ECH | B7: iShares MSCI Chile ETF | C7: 12-31-2020 | D7: 30.140603 | E7: -- | F7: 16450000 | H7: =(D7-D8)/D8 -> -0.095986714
A8: ECH | B8: iShares MSCI Chile ETF | C8: 12-31-2019 | D8: 33.340885 | E8: -- | F8: 15700000 | H8: =(D8-D9)/D9 -> -0.19816083
A9: ECH | B9: iShares MSCI Chile ETF | C9: 12-31- 2018 | D9: 41.580514 | E9: -- | F9: 10950000 | H9: =(D9-D10)/D10 -> -0.2078616
A10: ECH | B10: iShares MSCI Chile ETF | C10: 12-29-2017 | D10: 52.491476 | E10: -- | F10: 10600000 | H10: =(D10-D11)/D11 -> 0.40148437
A11: ECH | B11: iShares MSCI Chile ETF | C11: 12-30-2016 | D11: 37.4542 | E11: -- | F11: 10450000 | H11: =(D11-D12)/D12 -> 0.1558441
A12: ECH | B12: iShares MSCI Chile ETF | C12: 12-31-2015 | D12: 32.404197 | E12: -- | F12: 6050000 | H12: =(D12-D13)/D13 -> -0.19505471
A13: ECH | B13: iShares MSCI Chile ETF | C13: 12-31-2014 | D13: 40.256397 | E13: -- | F13: 6950000 | H13: =(D13-D14)/D14 -> -0.14054933
... A15: ECH | B15: iShares MSCI Chile ETF | C15: 12-31-2012 | D15: 62.314748 | E15: -- | F15: 8800000 | H15: =(D15-D16)/D16 -> 0.071919455
A16: ECH | B16: iShares MSCI Chile ETF | C16: 12-30-2011 | D16: 58.133797 | E16: -- | F16: 8700000 | G16: --
A17: EDEN | B17: iShares MSCI Denmark ETF | C17: 12-31-2025 | D17: 114.43115 | E17: -- | F17: 1750000 | H17: =(D17-D18)/D18 -> 0.070987589
A18: EDEN | B18: iShares MSCI Denmark ETF | C18: 12-31-2024 | D18: 106.84638 | E18: -- | F18: 2300000 | H18: =(D18-D19)/D19 -> -0.04997418
A19: EDEN | B19: iShares MSCI Denmark ETF | C19: 12-29-2023 | D19: 112.46682 | E19: -- | F19: 2250000 | H19: =(D19-D20)/D20 -> 0.15442606
A20: EDEN | B20: iShares MSCI Denmark ETF | C20: 12-30-2022 | D20: 97.422279 | E20: -- | F20: 2150000 | H20: =(D20-D21)/D21 -> -0.12510482
A21: EDEN | B21: iShares MSCI Denmark ETF | C21: 12-31-2021 | D21: 111.35309 | E21: -- | F21: 1650000 | H21: =(D21-D22)/D22 -> 0.133199
A22: EDEN | B22: iShares MSCI Denmark ETF | C22: 12-31-2020 | D22: 98.264371 | E22: -- | F22: 1700000 | H22: =(D22-D23)/D23 -> 0.73907704
A23: EDEN | B23: iShares MSCI Denmark ETF | C23: 12-31-2019 | D23: 56.503748 | E23: -- | F23: 1000000 | G23: -- | H23: =(D23-D24)/D24 -> -0.17871948
A24: EDEN | B24: iShares MSCI Denmark ETF | C24: 12-31- 2018 | D24: 68.799572 | E24: -- | F24: 550000 | H24: =(D24-D25)/D25 -> 0.017953286
A25: EDEN | B25: iShares MSCI Denmark ETF | C25: 12-29-2017 | D25: 67.586178 | E25: -- | F25: 900000 | H25: =(D25-D26)/D26 -> 0.31842376
A26: EDEN | B26: iShares MSCI Denmark ETF | C26: 12-30-2016 | D26: 51.262864 | E26: -- | F26: 1100000 | H26: =(D26-D27)/D27 -> -0.091134862
A27: EDEN | B27: iShares MSCI Denmark ETF | C27: 12-31-2015 | D27: 56.403158 | E27: -- | F27: 1550000 | H27: =(D27-D28)/D28 -> 0.19257294
A28: EDEN | B28: iShares MSCI Denmark ETF | C28: 12-31-2014 | D28: 47.295353 | E28: -- | F28: 1200000 | H28: =(D28-D29)/D29 -> 0.058331877
A29: EDEN | B29: iShares MSCI Denmark ETF | C29: 12-31-2013 | D29: 44.688584 | E29: -- | F29: 400000 | H29: =(D29-D30)/D30 -> 0.41793681
A30: EDEN | B30: iShares MSCI Denmark ETF | C30: 12-31-2012 | D30: 31.516626 | E30: -- | F30: 100000 | J30: des donnes jusqua 2012
A31: EFNL | B31: iShares MSCI Finland ETF | C31: 12-31-2025 | D31: 47.76 | E31: -- | F31: 650000 | G31: 48.05 | H31: =(D31-D32)/D32 -> 0.4763524
A32: EFNL | B32: iShares MSCI Finland ETF | C32: 12-31-2024 | D32: 32.35 | E32: -- | F32: 500000 | G32: 32.3 | H32: =(D32-D33)/D33 -> -0.095357942
A33: EFNL | B33: iShares MSCI Finland ETF | C33: 12-29-2023 | D33: 35.76 | E33: -- | F33: 550000 | G33: 35.7 | H33: =(D33-D34)/D34 -> -0.042570281
A34: EFNL | B34: iShares MSCI Finland ETF | C34: 12-30-2022 | D34: 37.35 | E34: -- | F34: 450000 | G34: 37.2 | H34: =(D34-D35)/D35 -> -0.22365413
A35: EFNL | B35: iShares MSCI Finland ETF | C35: 12-31-2021 | D35: 48.11 | E35: -- | F35: 550000 | G35: 48.13 | H35: =(D35-D36)/D36 -> 0.075324095
A36: EFNL | B36: iShares MSCI Finland ETF | C36: 12-31-2020 | D36: 44.74 | E36: -- | F36: 650000 | G36: -- | H36: =(D36-D37)/D37 -> 0.18234672
A37: EFNL | B37: iShares MSCI Finland ETF | C37: 12-31-2019 | D37: 37.84 | E37: -- | F37: 800000 | G37: -- | H37: =(D37-D38)/D38 -> 0.071044438
A38: EFNL | B38: iShares MSCI Finland ETF | C38: 12-31- 2018 | D38: 35.33 | E38: -- | F38: 850000 | G38: -- | H38: =(D38-D39)/D39 -> -0.10466295
A39: EFNL | B39: iShares MSCI Finland ETF | C39: 12-29-2017 | D39: 39.46 | E39: -- | F39: 1150000 | G39: -- | H39: =(D39-D40)/D40 -> 0.19322649
A40: EFNL | B40: iShares MSCI Finland ETF | C40: 12-30-2016 | D40: 33.07 | E40: -- | F40: 1100000 | G40: -- | H40: =(D40-D41)/D41 -> 0.0012110203
A41: EFNL | B41: iShares MSCI Finland ETF | C41: 12-31-2015 | D41: 33.03 | E41: -- | F41: 750000 | G41: -- | H41: =(D41-D42)/D42 -> 0.026732981
A42: EFNL | B42: iShares MSCI Finland ETF | C42: 12-31-2014 | D42: 32.17 | E42: -- | F42: 600000 | G42: -- | H42: =(D42-D43)/D43 -> -0.06699536
A43: EFNL | B43: iShares MSCI Finland ETF | C43: 12-31-2013 | D43: 34.48 | E43: -- | F43: 450000 | G43: -- | H43: =(D43-D44)/D44 -> 0.33954934
A44: EFNL | B44: iShares MSCI Finland ETF | C44: 12-31-2012 | D44: 25.74 | E44: -- | F44: 50000 | G44: --
A45: EIDO | B45: iShares MSCI Indonesia ETF | C45: 12-31-2025 | D45: 18.623924 | E45: -- | F45: 19450000 | G45: 18.656314 | H45: =(D45-D46)/D46 -> -0.0067083726
A46: EIDO | B46: iShares MSCI Indonesia ETF | C46: 12-31-2024 | D46: 18.749704 | E46: -- | F46: 14500000 | G46: 18.789304 | H46: =(D46-D47)/D47 -> -0.15726013
A47: EIDO | B47: iShares MSCI Indonesia ETF | C47: 12-29-2023 | D47: 22.248507 | E47: -- | F47: 19250000 | G47: 22.252523 | H47: =(D47-D48)/D48 -> -0.0078612539
A48: EIDO | B48: iShares MSCI Indonesia ETF | C48: 12-30-2022 | D48: 22.424794 | E48: -- | F48: 22400000 | G48: 22.435575 | H48: =(D48-D49)/D49 -> -0.028170024
A49: EIDO | B49: iShares MSCI Indonesia ETF | C49: 12-31-2021 | D49: 23.074812 | E49: -- | F49: 16150000 | G49: 23.059231 | H49: =(D49-D50)/D50 -> -0.0044055897
A50: EIDO | B50: iShares MSCI Indonesia ETF | C50: 12-31-2020 | D50: 23.17692 | E50: -- | F50: 16250000 | G50: -- | H50: =(D50-D51)/D51 -> -0.096894897
A51: EIDO | B51: iShares MSCI Indonesia ETF | C51: 12-31-2019 | D51: 25.663591 | E51: -- | F51: 19500000 | G51: -- | H51: =(D51-D52)/D52 -> 0.031063907
A52: EIDO | B52: iShares MSCI Indonesia ETF | C52: 12-31- 2018 | D52: 24.890398 | E52: -- | F52: 21200000 | G52: -- | H52: =(D52-D53)/D53 -> -0.12322216
A53: EIDO | B53: iShares MSCI Indonesia ETF | C53: 12-29-2017 | D53: 28.388489 | E53: -- | F53: 17850000 | G53: -- | H53: =(D53-D54)/D54 -> 0.16859995
A54: EIDO | B54: iShares MSCI Indonesia ETF | C54: 12-30-2016 | D54: 24.292735 | E54: -- | F54: 19750000 | G54: -- | H54: =(D54-D55)/D55 -> 0.15457248
A55: EIDO | B55: iShares MSCI Indonesia ETF | C55: 12-31-2015 | D55: 21.040459 | E55: -- | F55: 12750000 | G55: -- | H55: =(D55-D56)/D56 -> -0.23180838
A56: EIDO | B56: iShares MSCI Indonesia ETF | C56: 12-31-2014 | D56: 27.389597 | E56: -- | F56: 21650000 | G56: -- | H56: =(D56-D57)/D57 -> 0.22327451
A57: EIDO | B57: iShares MSCI Indonesia ETF | C57: 12-31-2013 | D57: 22.390393 | E57: -- | F57: 14650000 | G57: -- | H57: =(D57-D58)/D58 -> -0.2596538
A58: EIDO | B58: iShares MSCI Indonesia ETF | C58: 12-31-2012 | D58: 30.243139 | E58: -- | F58: 12800000
A59: ENOR | B59: iShares MSCI Norway ETF | C59: 12-31-2025 | D59: 28.784321 | E59: -- | F59: 1450000 | G59: 28.826916 | H59: =(D59-D60)/D60 -> 0.28677555
A60: ENOR | B60: iShares MSCI Norway ETF | C60: 12-31-2024 | D60: 22.369341 | E60: -- | F60: 1200000 | G60: 22.333039 | H60: =(D60-D61)/D61 -> -0.082797531
A61: ENOR | B61: iShares MSCI Norway ETF | C61: 12-29-2023 | D61: 24.388662 | E61: -- | F61: 1350000 | G61: 24.41341 | H61: =(D61-D62)/D62 -> -0.0099428865
A62: ENOR | B62: iShares MSCI Norway ETF | C62: 12-30-2022 | D62: 24.633591 | E62: -- | F62: 1200000 | G62: 24.516529 | H62: =(D62-D63)/D63 -> -0.15749243
A63: ENOR | B63: iShares MSCI Norway ETF | C63: 12-31-2021 | D63: 29.238421 | E63: -- | F63: 1950000 | G63: 29.311598 | H63: =(D63-D64)/D64 -> 0.15341824
A64: ENOR | B64: iShares MSCI Norway ETF | C64: 12-31-2020 | D64: 25.349366 | E64: -- | F64: 900000 | G64: -- | H64: =(D64-D65)/D65 -> 0.0062518183
A65: ENOR | B65: iShares MSCI Norway ETF | C65: 12-31-2019 | D65: 25.191871 | E65: -- | F65: 950000 | G65: -- | H65: =(D65-D66)/D66 -> 0.091044047
A66: ENOR | B66: iShares MSCI Norway ETF | C66: 12-31- 2018 | D66: 23.089692 | E66: -- | F66: 1400000 | G66: -- | H66: =(D66-D67)/D67 -> -0.10709248
A67: ENOR | B67: iShares MSCI Norway ETF | C67: 12-29-2017 | D67: 25.858996 | E67: -- | F67: 1400000 | G67: -- | H67: =(D67-D68)/D68 -> 0.18491706
A68: ENOR | B68: iShares MSCI Norway ETF | C68: 12-30-2016 | D68: 21.823465 | E68: -- | F68: 1400000 | G68: -- | H68: =(D68-D69)/D69 -> 0.14225011
A69: ENOR | B69: iShares MSCI Norway ETF | C69: 12-31-2015 | D69: 19.10568 | E69: -- | F69: 1000000 | G69: -- | H69: =(D69-D70)/D70 -> -0.18049854
A70: ENOR | B70: iShares MSCI Norway ETF | C70: 12-31-2014 | D70: 23.313784 | E70: -- | F70: 1000000 | G70: -- | H70: =(D70-D71)/D71 -> -0.24841556
A71: ENOR | B71: iShares MSCI Norway ETF | C71: 12-31-2013 | D71: 31.019514 | E71: -- | F71: 400000 | G71: -- | H71: =(D71-D72)/D72 -> 0.076305346
A72: ENOR | B72: iShares MSCI Norway ETF | C72: 12-31-2012 | D72: 28.820366 | E72: -- | F72: 300000 | G72: --
A73: ENZL | B73: iShares MSCI New Zealand ETF | C73: 12-31-2025 | D73: 45.244988 | E73: -- | F73: 1450000 | G73: 45.199913 | H73: =(D73-D74)/D74 -> -0.0053950272
A74: ENZL | B74: iShares MSCI New Zealand ETF | C74: 12-31-2024 | D74: 45.49041 | E74: -- | F74: 1750000 | G74: 45.549438 | H74: =(D74-D75)/D75 -> -0.065284338
A75: ENZL | B75: iShares MSCI New Zealand ETF | C75: 12-29-2023 | D75: 48.667645 | E75: -- | F75: 2350000 | G75: 48.751569 | H75: =(D75-D76)/D76 -> 0.0041181151
A76: ENZL | B76: iShares MSCI New Zealand ETF | C76: 12-30-2022 | D76: 48.468048 | E76: -- | F76: 2350000 | G76: 48.323047 | H76: =(D76-D77)/D77 -> -0.17996098
A77: ENZL | B77: iShares MSCI New Zealand ETF | C77: 12-31-2021 | D77: 59.104563 | E77: -- | F77: 2400000 | G77: 59.146819 | H77: =(D77-D78)/D78 -> -0.12976503
A78: ENZL | B78: iShares MSCI New Zealand ETF | C78: 12-31-2020 | D78: 67.917936 | E78: -- | F78: 3100000 | G78: -- | H78: =(D78-D79)/D79 -> 0.1761618
A79: ENZL | B79: iShares MSCI New Zealand ETF | C79: 12-31-2019 | D79: 57.745402 | E79: -- | F79: 3200000 | G79: -- | H79: =(D79-D80)/D80 -> 0.25131511
A80: ENZL | B80: iShares MSCI New Zealand ETF | C80: 12-31- 2018 | D80: 46.14777 | E80: -- | F80: 3050000 | G80: -- | H80: =(D80-D81)/D81 -> -0.036172029
A81: ENZL | B81: iShares MSCI New Zealand ETF | C81: 12-29-2017 | D81: 47.879675 | E81: -- | F81: 3250000 | G81: -- | H81: =(D81-D82)/D82 -> 0.19327381
A82: ENZL | B82: iShares MSCI New Zealand ETF | C82: 12-30-2016 | D82: 40.124634 | E82: -- | F82: 2850000 | G82: -- | H82: =(D82-D83)/D83 -> 0.059543173
A83: ENZL | B83: iShares MSCI New Zealand ETF | C83: 12-31-2015 | D83: 37.869749 | E83: -- | F83: 1950000 | G83: -- | H83: =(D83-D84)/D84 -> -0.055798632
A84: ENZL | B84: iShares MSCI New Zealand ETF | C84: 12-31-2014 | D84: 40.107704 | E84: -- | F84: 3350000 | G84: -- | H84: =(D84-D85)/D85 -> 0.074632963
A85: ENZL | B85: iShares MSCI New Zealand ETF | C85: 12-31-2013 | D85: 37.322235 | E85: -- | F85: 3650000 | G85: -- | H85: =(D85-D86)/D86 -> 0.092000571
A86: ENZL | B86: iShares MSCI New Zealand ETF | C86: 12-31-2012 | D86: 34.177853 | E86: -- | F86: 4600000 | G86: --
A87: EPHE | B87: iShares MSCI Philippines ETF | C87: 12-31-2025 | D87: 24.902717 | E87: -- | F87: 4550000 | G87: 24.912109 | H87: =(D87-D88)/D88 -> -0.024379621
A88: EPHE | B88: iShares MSCI Philippines ETF | C88: 12-31-2024 | D88: 25.525007 | E88: -- | F88: 3750000 | G88: 25.609366 | H88: =(D88-D89)/D89 -> -0.012620543
A89: EPHE | B89: iShares MSCI Philippines ETF | C89: 12-29-2023 | D89: 25.851264 | E89: -- | F89: 3800000 | G89: 25.857039 | H89: =(D89-D90)/D90 -> -0.022574329
A90: EPHE | B90: iShares MSCI Philippines ETF | C90: 12-30-2022 | D90: 26.448317 | E90: -- | F90: 4450000 | G90: 26.385482 | H90: =(D90-D91)/D91 -> -0.15749828
A91: EPHE | B91: iShares MSCI Philippines ETF | C91: 12-31-2021 | D91: 31.392597 | E91: -- | F91: 3950000 | G91: 31.394363 | H91: =(D91-D92)/D92 -> -0.031198326
A92: EPHE | B92: iShares MSCI Philippines ETF | C92: 12-31-2020 | D92: 32.403533 | E92: -- | F92: 4800000 | G92: -- | H92: =(D92-D93)/D93 -> -0.059128844
A93: EPHE | B93: iShares MSCI Philippines ETF | C93: 12-31-2019 | D93: 34.439926 | E93: -- | F93: 7100000 | G93: -- | H93: =(D93-D94)/D94 -> 0.079680566
A94: EPHE | B94: iShares MSCI Philippines ETF | C94: 12-31- 2018 | D94: 31.898255 | E94: -- | F94: 5700000 | G94: -- | H94: =(D94-D95)/D95 -> -0.17820546
A95: EPHE | B95: iShares MSCI Philippines ETF | C95: 12-29-2017 | D95: 38.815365 | E95: -- | F95: 4950000 | G95: -- | H95: =(D95-D96)/D96 -> 0.20395904
A96: EPHE | B96: iShares MSCI Philippines ETF | C96: 12-30-2016 | D96: 32.239772 | E96: -- | F96: 4400000 | G96: -- | H96: =(D96-D97)/D97 -> -0.057962152
A97: EPHE | B97: iShares MSCI Philippines ETF | C97: 12-31-2015 | D97: 34.223436 | E97: -- | F97: 7500000 | G97: -- | H97: =(D97-D98)/D98 -> -0.11267504
A98: EPHE | B98: iShares MSCI Philippines ETF | C98: 12-31-2014 | D98: 38.569225 | E98: -- | F98: 9650000 | G98: -- | H98: =(D98-D99)/D99 -> 0.23943981
A99: EPHE | B99: iShares MSCI Philippines ETF | C99: 12-31-2013 | D99: 31.118272 | E99: -- | F99: 8350000 | G99: -- | H99: =(D99-D100)/D100 -> -0.088131237
A100: EPHE | B100: iShares MSCI Philippines ETF | C100: 12-31-2012 | D100: 34.125823 | E100: -- | F100: 6400000 | G100: --
A101: EPOL | B101: iShares MSCI Poland ETF | C101: 12-31-2025 | D101: 35.011383 | E101: -- | F101: 13300000 | G101: 35.105906 | H101: =(D101-D102)/D102 -> 0.6752136
...

Sheet Datos
A1: Ticker | B1: Name | C1: ROL Index 2012-13 | D1: ROL Index 2014 | E1: ROL Index 2015 | F1: ROL Index 2016 | G1: ROL Index 2017-18 | H1: ROL Index 2019 | I1: ROL Index 2020 | J1: ROL Index 2021 | K1: ROL Index 2022 | L1: ROL Index 2023 | M1: ROL Index 2024 | N1: MSCI ESG Quality score 30-06-25 | O1: PDI | P1: IDV | Q1: MAS | R1: UAI | S1: LTO | T1: IVR
A2: ECH | B2: iShares MSCI Chile ETF | C2: 0.69 | D2: 0.68 | E2: 0.69 | F2: 0.69 | G2: 0.67 | H2: 0.68 | I2: 0.67 | J2: 0.66 | K2: 0.66 | L2: 0.66 | M2: 0.66 | N2: 5.92 | O2: 63 | P2: 23 | Q2: 28 | R2: 86 | S2: 31 | T2: 68
A3: EDEN | B3: iShares MSCI Denmark ETF | C3: 0.88 | D3: 0.88 | E3: 0.89 | F3: 0.89 | G3: 0.89 | H3: 0.9 | I3: 0.9 | J3: 0.9 | K3: 0.9 | L3: 0.9 | M3: 0.9 | N3: 8.16 | O3: 18 | P3: 74 | Q3: 16 | R3: 23 | S3: 35 | T3: 70
A4: EFNL | B4: iShares MSCI Finland ETF | C4: 0.87 | D4: 0.84 | E4: 0.87 | F4: 0.88 | G4: 0.87 | H4: 0.87 | I4: 0.87 | J4: 0.88 | K4: 0.87 | L4: 0.87 | M4: 0.87 | N4: 8.7 | O4: 33 | P4: 63 | Q4: 26 | R4: 59 | S4: 38 | T4: 57
A5: EIDO | B5: iShares MSCI Indonesia ETF | C5: 0.52 | D5: 0.52 | E5: 0.51 | F5: 0.52 | G5: 0.52 | H5: 0.52 | I5: 0.53 | J5: 0.52 | K5: 0.53 | L5: 0.53 | M5: 0.53 | N5: 5.83 | O5: 78 | P5: 14 | Q5: 46 | R5: 48 | S5: 62 | T5: 38
A6: ENOR | B6: iShares MSCI Norway ETF | C6: 0.87 | D6: 0.88 | E6: 0.88 | F6: 0.88 | G6: 0.89 | H6: 0.89 | I6: 0.89 | J6: 0.9 | K6: 0.89 | L6: 0.89 | M6: 0.89 | N6: 8.41 | O6: 31 | P6: 69 | Q6: 8 | R6: 50 | S6: 35 | T6: 55
A7: ENZL | B7: iShares MSCI New Zealand ETF | C7: 0.84 | D7: 0.83 | E7: 0.84 | F7: 0.83 | G7: 0.83 | H7: 0.82 | I7: 0.83 | J7: 0.83 | K7: 0.83 | L7: 0.83 | M7: 0.83 | N7: 7.33 | O7: 22 | P7: 79 | Q7: 58 | R7: 49 | S7: 33 | T7: 75
A8: EPHE | B8: iShares MSCI Philippines ETF | C8: 0.49 | D8: 0.5 | E8: 0.52 | F8: 0.51 | G8: 0.47 | H8: 0.47 | I8: 0.47 | J8: 0.46 | K8: 0.47 | L8: 0.46 | M8: 0.46 | N8: 4.02 | O8: 94 | P8: 32 | Q8: 64 | R8: 44 | S8: 27 | T8: 42
A9: EPOL | B9: iShares MSCI Poland ETF | C9: 0.72 | D9: 0.67 | E9: 0.72 | F9: 0.72 | G9: 0.67 | H9: 0.66 | I9: 0.66 | J9: 0.64 | K9: 0.64 | L9: 0.64 | M9: 0.66 | N9: 6.06 | O9: 68 | P9: 60 | Q9: 64 | R9: 93 | S9: 38 | T9: 29
A10: EWA | B10: iShares MSCI Australia ETF | C10: 0.83 | D10: 0.8 | E10: 0.81 | F10: 0.81 | G10: 0.81 | H10: 0.8 | I10: 0.8 | J10: 0.79 | K10: 0.79 | L10: 0.8 | M10: 0.8 | N10: 7.67 | O10: 38 | P10: 90 | Q10: 61 | R10: 51 | S10: 21 | T10: 71
A11: EWC | B11: iShares MSCI Canada ETF | C11: 0.79 | D11: 0.78 | E11: 0.79 | F11: 0.81 | G11: 0.81 | H11: 0.81 | I11: 0.81 | J11: 0.8 | K11: 0.8 | L11: 0.8 | M11: 0.8 | N11: 7.48 | O11: 39 | P11: 80 | Q11: 52 | R11: 48 | S11: 36 | T11: 68
A12: EWD | B12: iShares MSCI Sweden ETF | C12: 0.89 | D12: 0.85 | E12: 0.87 | F12: 0.86 | G12: 0.86 | H12: 0.86 | I12: 0.86 | J12: 0.86 | K12: 0.86 | L12: 0.85 | M12: 0.86 | N12: 7.12 | O12: 31 | P12: 71 | Q12: 5 | R12: 29 | S12: 53 | T12: 78
A13: EWG | B13: iShares MSCI Germany ETF | C13: 0.79 | D13: 0.8 | E13: 0.83 | F13: 0.84 | G13: 0.84 | H13: 0.84 | I13: 0.84 | J13: 0.84 | K13: 0.83 | L13: 0.83 | M13: 0.83 | N13: 7.7 | O13: 35 | P13: 67 | Q13: 66 | R13: 65 | S13: 83 | T13: 40
... A26: EWZ | B26: iShares MSCI Brazil ETF | C26: 0.58 | D26: 0.54 | E26: 0.55 | F26: 0.56 | G26: 0.54 | H26: 0.53 | I26: 0.52 | J26: 0.5 | K26: 0.49 | L26: 0.49 | M26: 0.5 | N26: 5.08 | O26: 69 | P26: 38 | Q26: 49 | R26: 76 | S26: 44 | T26: 59
A27: EZA | B27: iShares MSCI South Africa ETF | C27: 0.56 | D27: 0.55 | E27: 0.58 | F27: 0.59 | G27: 0.59 | H27: 0.58 | I27: 0.59 | J27: 0.58 | K27: 0.58 | L27: 0.57 | M27: 0.56 | N27: 7.45 | O27: / | P27: / | Q27: / | R27: / | S27: 34 | T27: 63
A28: INDA | B28: iShares MSCI India ETF | C28: 0.46 | D28: 0.48 | E28: 0.51 | F28: 0.52 | G28: 0.52 | H28: 0.51 | I28: 0.51 | J28: 0.5 | K28: 0.5 | L28: 0.49 | M28: 0.5 | N28: 5.36 | O28: 77 | P28: 48 | Q28: 56 | R28: 40 | S28: 51 | T28: 26
A29: MCHI | B29: iShares MSCI China ETF | C29: 0.48 | D29: 0.45 | E29: 0.48 | F29: 0.49 | G29: 0.5 | H29: 0.49 | I29: 0.48 | J29: 0.47 | K29: 0.47 | L29: 0.47 | M29: 0.47 | N29: 5.53 | O29: 80 | P29: 20 | Q29: 66 | R29: 30 | S29: 87 | T29: 24
A30: THD | B30: iShares MSCI Thailand ETF | C30: 0.53 | D30: 0.52 | E30: 0.52 | F30: 0.52 | G30: 0.51 | H30: 0.5 | I30: 0.51 | J30: 0.5 | K30: 0.5 | L30: 0.49 | M30: 0.5 | N30: 6.25 | O30: 64 | P30: 20 | Q30: 34 | R30: 64 | S30: 32 | T30: 45
A31: TUR | B31: iShares MSCI Turkey ETF | C31: 0.52 | D31: 0.5 | E31: 0.46 | F31: 0.44 | G31: 0.42 | H31: 0.43 | I31: 0.43 | J31: 0.42 | K31: 0.42 | L31: 0.41 | M31: 0.42 | N31: 5.01 | O31: 66 | P31: 37 | Q31: 45 | R31: 85 | S31: 46 | T31: 49

Sheet etf
A1: Ticker | B1: Name | C1: Incept. Date | D1: Gross Expense Ratio (%) | E1: Net Expense Ratio (%) | F1: Net Assets (USD) | G1: Net Assets as of | H1: Asset Class | I1: Sub Asset Class | J1: Region | K1: Market | L1: Location | M1: Investment Style | N1: Key Facts | R1: Avg. Annual Return: NAV Quarterly | Y1: Avg. Annual Return: Price Quarterly | AF1: Avg. Annual Return: NAV Monthly | AM1: Avg. Annual Return: Price Monthly | AT1: Yield
N2: 12m Trailing Yield (%) | O2: As of | P2: YTD Return (%) | Q2: Per. As of | R2: YTD (%) | S2: 1Y (%) | T2: 3Y (%) | U2: 5Y (%) | V2: 10Y (%) | W2: Incept. (%) | X2: Per. As of | Y2: YTD (%) | Z2: 1Y (%) | AA2: 3Y (%) | AB2: 5Y (%) | AC2: 10Y (%) | AD2: Incept. (%) | AE2: Per. As of | AF2: YTD (%) | AG2: 1Y (%) | AH2: 3Y (%) | AI2: 5Y (%) | AJ2: 10Y (%) | AK2: Incept. (%) | AL2: Per. As of | AM2: YTD (%) | AN2: 1Y (%) | AO2: 3Y (%) | AP2: 5Y (%) | AQ2: 10Y (%) | AR2: Incept. (%) | AS2: Per. As of | AT2: 12m Trailing Yield (%) | AU2: As of | AV2: 30-Day SEC Yield (%) | AW2: Unsubsidized Yield (%) | AX2: As of
A3: EEM | B3: iShares MSCI Emerging Markets ETF | C3: 37718 | D3: 0.72 | E3: 0.72 | F3: 1.9468834e+10 | G3: 45909 | H3: Equity | I3: Large/Mid Cap | J3: Global | K3: Emerging | L3: Broad | M3: Index | N3: 2.3684 | O3: 45898 | P3: 22.983915 | Q3: 45909 | R3: 15.59 | S3: 15.71 | T3: 9 | U3: 6.11 | V3: 4.18 | W3: 8.81 | X3: 45838 | Y3: 16.45 | Z3: 16.28 | AA3: 9.05 | AB3: 6.24 | AC3: 4.3 | AD3: 8.82 | AE3: 45838 | AF3: 19.57 | AG3: 17.69 | AH3: 10.6 | AI3: 4.59 | AJ3: 6.3 | AK3: 8.91 | AL3: 45900 | AM3: 20.37 | AN3: 18.03 | AO3: 10.88 | AP3: 4.63 | AQ3: 6.31 | AR3: 8.91 | AS3: 45900 | AT3: 2.3684 | AU3: 45898 | AV3: 1.5113 | AW3: 1.5113 | AX3: 45898
A4: EWJ | B4: iShares MSCI Japan ETF | C4: 35136 | D4: 0.5 | E4: 0.5 | F4: 1.5616649e+10 | G4: 45909 | H4: Equity | I4: Large/Mid Cap | J4: Asia Pacific | K4: Developed | L4: Japan | M4: Index | N4: 2.1204 | O4: 45898 | P4: 20.397027 | Q4: 45909 | R4: 13.09 | S4: 13.05 | T4: 14.55 | U4: 8.35 | V4: 5.69 | W4: 2.05 | X4: 45838 | Y4: 12.63 | Z4: 12.49 | AA4: 14.43 | AB4: 8.34 | AC4: 5.68 | AD4: 2.04 | AE4: 45838 | AF4: 17.56 | AG4: 10.63 | AH4: 15.35 | AI4: 7.97 | AJ4: 6.69 | AK4: 2.17 | AL4: 45900 | AM4: 17.6 | AN4: 11.37 | AO4: 15.54 | AP4: 8.07 | AQ4: 6.74 | AR4: 2.18 | AS4: 45900 | AT4: 2.1204 | AU4: 45898 | AV4: 1.4654 | AW4: 1.4654 | AX4: 45898
A5: INDA | B5: iShares MSCI India ETF | C5: 40941 | D5: 0.62 | E5: 0.62 | F5: 9.2908244e+09 | G5: 45909 | H5: Equity | I5: Large/Mid Cap | J5: Asia Pacific | K5: Emerging | L5: India | M5: Index | N5: 0.7692 | O5: 45898 | P5: 0.053691306 | Q5: 45909 | R5: 5.13 | S5: 0.44 | T5: 12.35 | U5: 15.38 | V5: 7.56 | W5: 7.12 | X5: 45838 | Y5: 5.78 | Z5: 0.55 | AA5: 12.59 | AB5: 15.62 | AC5: 7.61 | AD5: 7.14 | AE5: 45838 | AF5: -1.71 | AG5: -9.33 | AH5: 6.65 | AI5: 10.86 | AJ5: 7.65 | AK5: 6.5 | AL5: 45900 | AM5: -1.25 | AN5: -9.29 | AO5: 6.84 | AP5: 10.9 | AQ5: 7.66 | AR5: 6.5 | AS5: 45900 | AT5: 0.7692 | AU5: 45898 | AV5: 0.4335 | AW5: 0.4335 | AX5: 45898
A6: MCHI | B6: iShares MSCI China ETF | C6: 40631 | D6: 0.59 | E6: 0.59 | F6: 8.1237849e+09 | G6: 45909 | H6: Equity | I6: Large/Mid Cap | J6: Asia Pacific | K6: Emerging | L6: China | M6: Index | N6: 2.3326 | O6: 45898 | P6: 35.082503 | Q6: 45909 | R6: 18.06 | S6: 33.84 | T6: 2.49 | U6: -1.45 | V6: 1.61 | W6: 2.72 | X6: 45838 | Y6: 18.73 | Z6: 34.42 | AA6: 2.33 | AB6: -1.34 | AC6: 1.71 | AD6: 2.73 | AE6: 45838 | AF6: 31.2 | AG6: 49.98 | AH6: 10.04 | AI6: -2.2 | AJ6: 5.17 | AK6: 3.44 | AL6: 45900 | AM6: 32.11 | AN6: 50.79 | AO6: 10.23 | AP6: -2.08 | AQ6: 5.28 | AR6: 3.46 | AS6: 45900 | AT6: 2.3326 | AU6: 45898 | AV6: 1.343 | AW6: 1.343 | AX6: 45898
A7: IOO | B7: iShares Global 100 ETF | C7: 36865 | D7: 0.4 | E7: 0.4 | F7: 7.1010932e+09 | G7: 45909 | H7: Equity | I7: Large Cap | J7: Global | K7: Developed | L7: Broad | M7: Index | N7: 1.0024 | O7: 45898 | P7: 16.264343 | Q7: 45909 | R7: 7.77 | S7: 13.05 | T7: 20.56 | U7: 17.15 | V7: 13.29 | W7: 6.78 | X7: 45838 | Y7: 7.72 | Z7: 12.87 | AA7: 20.59 | AB7: 17.14 | AC7: 13.27 | AD7: 6.78 | AE7: 45838 | AF7: 14.65 | AG7: 18.24 | AH7: 22.06 | AI7: 15.79 | AJ7: 14.6 | AK7: 7 | AL7: 45900 | AM7: 14.65 | AN7: 18.25 | AO7: 22.04 | AP7: 15.81 | AQ7: 14.63 | AR7: 7 | AS7: 45900 | AT7: 1.0024 | AU7: 45898 | AV7: 0.9263 | AW7: 0.9263 | AX7: 45898
A8: IEUR | B8: iShares Core MSCI Europe ETF | C8: 41800 | D8: 0.09 | E8: 0.09 | F8: 6.8888057e+09 | G8: 45909 | H8: Equity | I8: All Cap | J8: Europe | K8: Developed | L8: Broad | M8: Index | N8: 3.0808 | O8: 45869 | P8: 26.399463 | Q8: 45909 | R8: 24.41 | S8: 20.11 | T8: 17.32 | U8: 12.58 | V8: 7.08 | W8: 5.62 | X8: 45838 | Y8: 25.01 | Z8: 20.02 | AA8: 17.33 | AB8: 12.56 | AC8: 7.06 | AD8: 5.63 | AE8: 45838 | AF8: 25.705964 | AG8: 13.792156 | AH8: 18.725605 | AI8: 10.925596 | AJ8: 7.61828 | AK8: 5.634477 | AL8: 45900 | AM8: 26.029146 | AN8: 13.846427 | AO8: 18.737996 | AP8: 10.985665 | AQ8: 7.600042 | AR8: 5.634477 | AS8: 45900 | AT8: 3.0808 | AU8: 45869 | AV8: 2.5943 | AW8: 2.5943 | AX8: 45869
A9: EWT | B9: iShares MSCI Taiwan ETF | C9: 36697 | D9: 0.59 | E9: 0.59 | F9: 6.4027064e+09 | G9: 45909 | H9: Equity | I9: Large/Mid Cap | J9: Asia Pacific | K9: Emerging | L9: Taiwan | M9: Index | N9: 2.0444 | O9: 45898 | P9: 18.559255 | Q9: 45909 | R9: 9.79 | S9: 8.75 | T9: 15.78 | U9: 15.36 | V9: 11.48 | W9: 4.96 | X9: 45838 | Y9: 10.9 | Z9: 9.39 | AA9: 16.08 | AB9: 15.47 | AC9: 11.63 | AD9: 4.97 | AE9: 45838 | AF9: 12.88 | AG9: 12.39 | AH9: 16.96 | AI9: 13.92 | AJ9: 13.59 | AK9: 5.05 | AL9: 45900 | AM9: 13.64 | AN9: 12.9 | AO9: 17.18 | AP9: 14 | AQ9: 13.78 | AR9: 5.04 | AS9: 45900 | AT9: 2.0444 | AU9: 45898 | AV9: 2.0126 | AW9: 2.0126 | AX9: 45898
A10: URTH | B10: iShares MSCI World ETF | C10: 40918 | D10: 0.24 | E10: 0.24 | F10: 5.7451719e+09 | G10: 45909 | H10: Equity | I10: Large/Mid Cap | J10: Global | K10: Developed | L10: Broad | M10: Index | N10: 1.3455 | O10: 45898 | P10: 14.957069 | Q10: 45909 | R10: 9.75 | S10: 16.5 | T10: 18.46 | U10: 14.73 | V10: 10.9 | W10: 11.56 | X10: 45838 | Y10: 9.76 | Z10: 16.51 | AA10: 18.46 | AB10: 14.76 | AC10: 10.93 | AD10: 11.56 | AE10: 45838 | AF10: 13.9 | AG10: 15.68 | AH10: 18.7 | AI10: 13.04 | AJ10: 11.87 | AK10: 11.71 | AL10: 45900 | AM10: 13.97 | AN10: 15.74 | AO10: 18.71 | AP10: 13.09 | AQ10: 11.85 | AR10: 11.72 | AS10: 45900 | AT10: 1.3455 | AU10: 45898 | AV10: 1.3005 | AW10: 1.3005 | AX10: 45898
A11: EWZ | B11: iShares MSCI Brazil ETF | C11: 36717 | D11: 0.59 | E11: 0.59 | F11: 5.4436768e+09 | G11: 45909 | H11: Equity | I11: Large/Mid Cap | J11: Latin America | K11: Emerging | L11: Brazil | M11: Index | N11: 5.4684 | O11: 45898 | P11: 32.508969 | Q11: 45909 | R11: 29.25 | S11: 12.14 | T11: 9.72 | U11: 7.96 | V11: 3.67 | W11: 5.3 | X11: 45838 | Y11: 30.5 | Z11: 12.37 | AA11: 9.78 | AB11: 7.75 | AC11: 3.71 | AD11: 5.29 | AE11: 45838 | AF11: 32.08 | AG11: 5.03 | AH11: 6.6 | AI11: 7.54 | AJ11: 6.88 | AK11: 5.35 | AL11: 45900 | AM11: 33.44 | AN11: 5.13 | AO11: 6.68 | AP11: 7.46 | AQ11: 6.85 | AR11: 5.35 | AS11: 45900 | AT11: 5.4684 | AU11: 45898 | AV11: 4.9924 | AW11: 4.9924 | AX11: 45898
A12: EWY | B12: iShares MSCI South Korea ETF | C12: 36655 | D12: 0.59 | E12: 0.59 | F12: 5.2608399e+09 | G12: 45909 | H12: Equity | I12: Large/Mid Cap | J12: Asia Pacific | K12: Emerging | L12: South Korea | M12: Index | N12: 1.792 | O12: 45898 | P12: 47.369508 | Q12: 45909 | R12: 40.93 | S12: 10.73 | T12: 9.65 | U12: 6.59 | V12: 4.54 | W12: 6.43 | X12: 45838 | Y12: 41.05 | Z12: 11.24 | AA12: 9.47 | AB12: 6.58 | AC12: 4.65 | AD12: 6.44 | AE12: 45838 | AF12: 42.45 | AG12: 13.03 | AH12: 9.66 | AI12: 4.7 | AJ12: 6.17 | AK12: 6.44 | AL12: 45900 | AM12: 41.95 | AN12: 12.96 | AO12: 9.88 | AP12: 4.63 | AQ12: 6.21 | AR12: 6.42 | AS12: 45900 | AT12: 1.792 | AU12: 45898 | AV12: 1.0629 | AW12: 1.0629 | AX12: 45898
A13: EWC | B13: iShares MSCI Canada ETF | C13: 35136 | D13: 0.5 | E13: 0.5 | F13: 3.1950053e+09 | G13: 45909 | H13: Equity | I13: Large/Mid Cap | J13: North America | K13: Developed | L13: Canada | M13: Index | N13: 1.756 | O13: 45898 | P13: 23.134871 | Q13: 45909 | R13: 15.57 | S13: 26.97 | T13: 13.63 | U13: 14.78 | V13: 7.95 | W13: 8.38 | X13: 45838 | Y13: 15.42 | Z13: 27.09 | AA13: 13.64 | AB13: 14.71 | AC13: 7.95 | AD13: 8.38 | AE13: 45838 | AF13: 21.95 | AG13: 22.86 | AH13: 15.65 | AI13: 13.52 | AJ13: 9.67 | AK13: 8.53 | AL13: 45900 | AM13: 21.88 | AN13: 22.93 | AO13: 15.71 | AP13: 13.58 | AQ13: 9.57 | AR13: 8.53 | AS13: 45900 | AT13: 1.756 | AU13: 45898 | AV13: 1.647 | AW13: 1.647 | AX13: 45898
A14: EWU | B14: iShares MSCI United Kingdom ETF | C14: 35136 | D14: 0.5 | E14: 0.5 | F14: 2.8797441e+09 | G14: 45909 | H14: Equity | I14: Large/Mid Cap | J14: Europe | K14: Developed | L14: United Kingdom | M14: Index | N14: 3.7094 | O14: 45898 | P14: 25.254361 | Q14: 45909 | R14: 19.38 | S14: 19.71 | T14: 14.4 | U14: 13.4 | V14: 4.9 | W14: 5.56 | X14: 45838 | Y14: 19.57 | Z14: 18.65 | AA14: 14.24 | AB14: 13.3 | AC14: 4.88 | AD14: 5.54 | AE14: 45838 | AF14: 24.58 | AG14: 15.49 | AH14: 17.28 | AI14: 13.29 | AJ14: 6 | AK14: 5.68 | AL14: 45900 | AM14: 24.8 | AN14: 15.1 | AO14: 17.27 | AP14: 13.5 | AQ14: 6.05 | AR14: 5.66 | AS14: 45900 | AT14: 3.7094 | AU14: 45898 | AV14: 2.8972 | AW14: 2.8972 | AX14: 45898
... A26: INDY | B26: iShares India 50 ETF | C26: 40135 | D26: 0.65 | E26: 0.65 | F26: 6.4788026e+08 | G26: 45909 | H26: Equity | I26: Large Cap | J26: Asia Pacific | K26: Emerging | L26: India | M26: Index | N26: 0 | O26: 45898 | P26: 1.19575 | Q26: 45909 | R26: 6.56 | S26: 1.67 | T26: 11.24 | U26: 14.45 | V26: 7.55 | W26: 6.23 | X26: 45838 | Y26: 6.96 | Z26: 1.5 | AA26: 11.4 | AB26: 14.47 | AC26: 7.6 | AD26: 6.23 | AE26: 45838 | AF26: -0.3 | AG26: -7.88 | AH26: 6.09 | AI26: 10.16 | AJ26: 7.77 | AK26: 5.72 | AL26: 45900 | AM26: 0.12 | AN26: -7.67 | AO26: 6.22 | AP26: 10.21 | AQ26: 7.82 | AR26: 5.72 | AS26: 45900 | AT26: 0 | AU26: 45898 | AV26: 0.5417 | AW26: 0.5417 | AX26: 45898
A27: KSA | B27: iShares MSCI Saudi Arabia ETF | C27: 42263 | D27: 0.75 | E27: 0.75 | F27: 5.6131213e+08 | G27: 45909 | H27: Equity | I27: All Cap | J27: Middle East and Africa | K27: Emerging | L27: Saudi Arabia | M27: Index | N27: 3.797 | O27: 45898 | P27: -8.2583454 | Q27: 45909 | R27: -4.34 | S27: -2.15 | T27: 0.46 | U27: 10.16 | V27: - | W27: 7.05 | X27: 45838 | Y27: -4.04 | Z27: -1.64 | AA27: 0.51 | AB27: 10.37 | AC27: - | AD27: 7.06 | AE27: 45838 | AF27: -6.79 | AG27: -8.01 | AH27: -2.78 | AI27: 7.92 | AJ27: - | AK27: 6.65 | AL27: 45900 | AM27: -6.98 | AN27: -8.59 | AO27: -2.79 | AP27: 7.71 | AQ27: - | AR27: 6.6 | AS27: 45900 | AT27: 3.797 | AU27: 45898 | AV27: 2.8149 | AW27: 2.8149 | AX27: 45898
A28: EPOL | B28: iShares MSCI Poland ETF | C28: 40323 | D28: 0.6 | E28: 0.6 | F28: 4.5193192e+08 | G28: 45909 | H28: Equity | I28: All Cap | J28: Europe | K28: Emerging | L28: Poland | M28: Index | N28: 4.2267 | O28: 45898 | P28: 57.702201 | Q28: 45909 | R28: 56.57 | S28: 38.12 | T28: 35.45 | U28: 17.44 | V28: 6.1 | W28: 4.97 | X28: 45838 | Y28: 57.27 | Z28: 39.02 | AA28: 35.49 | AB28: 17.63 | AC28: 6.15 | AD28: 4.99 | AE28: 45838 | AF28: 54.3 | AG28: 35.92 | AH28: 41.58 | AI28: 15 | AJ28: 6.55 | AK28: 4.81 | AL28: 45900 | AM28: 54.54 | AN28: 36.39 | AO28: 41.76 | AP28: 15.17 | AQ28: 6.51 | AR28: 4.81 | AS28: 45900 | AT28: 4.2267 | AU28: 45898 | AV28: 3.2686 | AW28: 3.2686 | AX28: 45898
A29: EZA | B29: iShares MSCI South Africa ETF | C29: 37655 | D29: 0.59 | E29: 0.59 | F29: 4.2843899e+08 | G29: 45909 | H29: Equity | I29: Large/Mid Cap | J29: Middle East and Africa | K29: Emerging | L29: South Africa | M29: Index | N29: 5.3185 | O29: 45898 | P29: 41.959949 | Q29: 45909 | R29: 29.34 | S29: 31.2 | T29: 12.79 | U29: 13.2 | V29: 2.51 | W29: 8.44 | X29: 45838 | Y29: 29.76 | Z29: 32.24 | AA29: 12.72 | AB29: 13.4 | AC29: 2.64 | AD29: 8.46 | AE29: 45838 | AF29: 38.31 | AG29: 30.34 | AH29: 17.45 | AI29: 13.59 | AJ29: 4.64 | AK29: 8.7 | AL29: 45900 | AM29: 39.23 | AN29: 30.88 | AO29: 17.9 | AP29: 13.78 | AQ29: 4.71 | AR29: 8.73 | AS29: 45900 | AT29: 5.3185 | AU29: 45898 | AV29: 1.8499 | AW29: 1.8499 | AX29: 45898
A30: EIS | B30: iShares MSCI Israel ETF | C30: 39533 | D30: 0.59 | E30: 0.59 | F30: 4.1855719e+08 | G30: 45909 | H30: Equity | I30: All Cap | J30: Europe | K30: Developed | L30: Israel | M30: Index | N30: 1.0953 | O30: 45898 | P30: 27.721752 | Q30: 45909 | R30: 23.65 | S30: 57.01 | T30: 18.44 | U30: 14.26 | V30: 7.77 | W30: 5.68 | X30: 45838 | Y30: 23.84 | Z30: 58.28 | AA30: 18.67 | AB30: 14.32 | AC30: 7.85 | AD30: 5.73 | AE30: 45838 | AF30: 24.52 | AG30: 43.11 | AH30: 14.23 | AI30: 12.23 | AJ30: 8.05 | AK30: 5.67 | AL30: 45900 | AM30: 23.71 | AN30: 43.1 | AO30: 14.2 | AP30: 12.31 | AQ30: 8.07 | AR30: 5.66 | AS30: 45900 | AT30: 1.0953 | AU30: 45898 | AV30: 1.0129 | AW30: 1.0129 | AX30: 45898
A31: EWQ | B31: iShares MSCI France ETF | C31: 35136 | D31: 0.5 | E31: 0.5 | F31: 3.867682e+08 | G31: 45909 | H31: Equity | I31: Large/Mid Cap | J31: Europe | K31: Developed | L31: France | M31: Index | N31: 2.876 | O31: 45898 | P31: 22.099266 | Q31: 45909 | R31: 21.52 | S31: 17.21 | T31: 15.78 | U31: 12.97 | V31: 8.12 | W31: 7 | X31: 45838 | Y31: 21.98 | Z31: 16.72 | AA31: 15.8 | AB31: 12.83 | AC31: 8.09 | AD31: 7 | AE31: 45838 | AF31: 21.13 | AG31: 10.15 | AH31: 16.33 | AI31: 11.24 | AJ31: 8.35 | AK31: 6.94 | AL31: 45900 | AM31: 21.38 | AN31: 10.03 | AO31: 16.09 | AP31: 11.24 | AQ31: 8.33 | AR31: 6.94 | AS31: 45900 | AT31: 2.876 | AU31: 45898 | AV31: 2.1127 | AW31: 2.1127 | AX31: 45898
A32: EWD | B32: iShares MSCI Sweden ETF | C32: 35136 | D32: 0.54 | E32: 0.54 | F32: 3.2632659e+08 | G32: 45909 | H32: Equity | I32: Large/Mid Cap | J32: Europe | K32: Developed | L32: Sweden | M32: Index | N32: 2.1782 | O32: 45898 | P32: 29.308966 | Q32: 45909 | R32: 25.22 | S32: 16.42 | T32: 17.23 | U32: 11.6 | V32: 7.13 | W32: 8.31 | X32: 45838 | Y32: 25.29 | Z32: 16.2 | AA32: 17.16 | AB32: 11.55 | AC32: 7.13 | AD32: 8.3 | AE32: 45838 | AF32: 26.83 | AG32: 12.37 | AH32: 18.17 | AI32: 8.74 | AJ32: 7.8 | AK32: 8.31 | AL32: 45900 | AM32: 27.07 | AN32: 12.48 | AO32: 18.2 | AP32: 8.77 | AQ32: 7.78 | AR32: 8.3 | AS32: 45900 | AT32: 2.1782 | AU32: 45898 | AV32: 1.3667 | AW32: 1.3667 | AX32: 45898
A33: EIDO | B33: iShares MSCI Indonesia ETF | C33: 40303 | D33: 0.59 | E33: 0.59 | F33: 3.2340575e+08 | G33: 45909 | H33: Equity | I33: All Cap | J33: Asia Pacific | K33: Emerging | L33: Indonesia | M33: Index | N33: 4.4327 | O33: 45898 | P33: -6.2932619 | Q33: 45909 | R33: -4.02 | S33: -5.5 | T33: -4.21 | U33: 1.91 | V33: -0.66 | W33: 0.01 | X33: 45838 | Y33: -2.03 | Z33: -4.57 | AA33: -4.03 | AB33: 2.6 | AC33: -0.48 | AD33: 0.05 | AE33: 45838 | AF33: -3.37 | AG33: -16.24 | AH33: -6.16 | AI33: 0.82 | AJ33: 0.91 | AK33: 0.05 | AL33: 45900 | AM33: -1.81 | AN33: -15.34 | AO33: -5.85 | AP33: 0.92 | AQ33: 1.06 | AR33: 0.07 | AS33: 45900 | AT33: 4.4327 | AU33: 45898 | AV33: 4.0135 | AW33: 4.0135 | AX33: 45898
A34: EWM | B34: iShares MSCI Malaysia ETF | C34: 35136 | D34: 0.5 | E34: 0.5 | F34: 2.4078562e+08 | G34: 45909 | H34: Equity | I34: Large/Mid Cap | J34: Asia Pacific | K34: Emerging | L34: Malaysia | M34: Index | N34: 3.8705 | O34: 45898 | P34: 3.877885 | Q34: 45909 | R34: 0.44 | S34: 12.56 | T34: 6.94 | U34: 2.78 | V34: 0.12 | W34: 1.52 | X34: 45838 | Y34: 1.33 | Z34: 12.75 | AA34: 7.03 | AB34: 3.03 | AC34: 0.08 | AD34: 1.49 | AE34: 45838 | AF34: 2.6 | AG34: -0.48 | AH34: 6.81 | AI34: 2.36 | AJ34: 2.03 | AK34: 1.59 | AL34: 45900 | AM34: 3.54 | AN34: -0.18 | AO34: 7.21 | AP34: 2.42 | AQ34: 2.04 | AR34: 1.56 | AS34: 45900 | AT34: 3.8705 | AU34: 45898 | AV34: 3.6565 | AW34: 3.6565 | AX34: 45898
A35: THD | B35: iShares MSCI Thailand ETF | C35: 39533 | D35: 0.59 | E35: 0.59 | F35: 2.3341128e+08 | G35: 45909 | H35: Equity | I35: All Cap | J35: Asia Pacific | K35: Emerging | L35: Thailand | M35: Index | N35: 3.4213 | O35: 45898 | P35: 1.6354527 | Q35: 45909 | R35: -15.6 | S35: -4.04 | T35: -7.04 | U35: -3.87 | V35: -1.24 | W35: 2.83 | X35: 45838 | Y35: -14.56 | Z35: -3.63 | AA35: -7.05 | AB35: -3.76 | AC35: -1.15 | AD35: 2.85 | AE35: 45838 | AF35: -3.86 | AG35: -4.02 | AH35: -3.7 | AI35: -0.58 | AJ35: 1.49 | AK35: 3.58 | AL35: 45900 | AM35: -3.08 | AN35: -3.63 | AO35: -3.5 | AP35: -0.61 | AQ35: 1.55 | AR35: 3.57 | AS35: 45900 | AT35: 3.4213 | AU35: 45898 | AV35: 3.1125 | AW35: 3.1125 | AX35: 45898
A36: TOK | B36: iShares MSCI Kokusai ETF | C36: 39426 | D36: 0.25 | E36: 0.25 | F36: 2.3122829e+08 | G36: 45909 | H36: Equity | I36: Large/Mid Cap | J36: Global | K36: Developed | L36: Broad | M36: Index | N36: 1.4692 | O36: 45898 | P36: 14.631529 | Q36: 45909 | R36: 9.57 | S36: 16.71 | T36: 18.88 | U36: 15.31 | V36: 11.32 | W36: 7.86 | X36: 45838 | Y36: 9.38 | Z36: 16.52 | AA36: 18.88 | AB36: 15.11 | AC36: 11.24 | AD36: 7.84 | AE36: 45838 | AF36: 13.67 | AG36: 15.97 | AH36: 19.09 | AI36: 13.49 | AJ36: 12.28 | AK36: 8.01 | AL36: 45900 | AM36: 13.44 | AN36: 16.05 | AO36: 18.94 | AP36: 13.34 | AQ36: 12.21 | AR36: 7.99 | AS36: 45900 | AT36: 1.4692 | AU36: 45898 | AV36: 1.2687 | AW36: 1.2687 | AX36: 45898
A37: EDEN | B37: iShares MSCI Denmark ETF | C37: 40933 | D37: 0.53 | E37: 0.53 | F37: 1.8476208e+08 | G37: 45909 | H37: Equity | I37: All Cap | J37: Europe | K37: Developed | L37: Denmark | M37: Index | N37: 1.815 | O37: 45898 | P37: 3.1220336 | Q37: 45909 | R37: 8.16 | S37: -7.54 | T37: 11.52 | U37: 10.84 | V37: 9.47 | W37: 13.26 | X37: 45838 | Y37: 8.4 | Z37: -8.03 | AA37: 11.38 | AB37: 10.65 | AC37: 9.44 | AD37: 13.24 | AE37: 45838 | AF37: 4.12 | AG37: -14.24 | AH37: 10.16 | AI37: 6.85 | AJ37: 9 | AK37: 12.77 | AL37: 45900 | AM37: 4.56 | AN37: -14.28 | AO37: 10.2 | AP37: 6.99 | AQ37: 8.99 | AR37: 12.77 | AS37: 45900 | AT37: 1.815 | AU37: 45898 | AV37: 1.8296 | AW37: 1.8296 | AX37: 45898
A38: UAE | B38: iShares MSCI UAE ETF | C38: 41758 | D38: 0.6 | E38: 0.6 | F38: 1.6518134e+08 | G38: 45909 | H38: Equity | I38: All Cap | J38: Middle East and Africa | K38: Emerging | L38: United Arab Emirates | M38: Index | N38: 3.1639 | O38: 45898 | P38: 20.054704 | Q38: 45909 | R38: 17.2 | S38: 40.03 | T38: 9.98 | U38: 17.07 | V38: 3.34 | W38: 1.44 | X38: 45838 | Y38: 17.59 | Z38: 40.93 | AA38: 10.35 | AB38: 17.58 | AC38: 3.42 | AD38: 1.48 | AE38: 45838 | AF38: 22.14 | AG38: 35.38 | AH38: 10.27 | AI38: 16.41 | AJ38: 4.71 | AK38: 1.79 | AL38: 45900 | AM38: 21.74 | AN38: 33.74 | AO38: 9.8 | AP38: 16.69 | AQ38: 4.58 | AR38: 1.77 | AS38: 45900 | AT38: 3.1639 | AU38: 45898 | AV38: 3.9766 | AW38: 3.9766 | AX38: 45898
A39: TUR | B39: iShares MSCI Turkey ETF | C39: 39533 | D39: 0.59 | E39: 0.59 | F39: 1.6201496e+08 | G39: 45909 | H39: Equity | I39: All Cap | J39: Europe | K39: Emerging | L39: Turkey | M39: Index | N39: 1.7975 | O39: 45869 | P39: -8.2146946 | Q39: 45909 | R39: -9.63 | S39: -22.17 | T39: 22.55 | U39: 9.73 | V39: -0.66 | W39: -0.07 | X39: 45838 | Y39: -8.67 | Z39: -21.75 | AA39: 22.59 | AB39: 9.98 | AC39: -0.58 | AD39: -0.06 | AE39: 45838 | AF39: -1.155368 | AG39: -3.395708 | AH39: 19.18199 | AI39: 15.345204 | AJ39: 1.963514 | AK39: 0.447082 | AL39: 45900 | AM39: -0.091893 | AN39: -2.945442 | AO39: 19.432012 | AP39: 15.409613 | AQ39: 1.987353 | AR39: 0.447082 | AS39: 45900 | AT39: 1.7975 | AU39: 45869 | AV39: 1.6353 | AW39: 1.6353 | AX39: 45869
... A41: EPHE | B41: iShares MSCI Philippines ETF | C41: 40449 | D41: 0.59 | E41: 0.59 | F41: 1.0427821e+08 | G41: 45909 | H41: Equity | I41: All Cap | J41: Asia Pacific | K41: Emerging | L41: Philippines | M41: Index | N41: 2.0937 | O41: 45898 | P41: 3.3564309 | Q41: 45909 | R41: 7.47 | S41: 13.69 | T41: 4.49 | U41: 1.58 | V41: -2.46 | W41: 1.7 | X41: 45838 | Y41: 9.64 | Z41: 14.58 | AA41: 4.31 | AB41: 1.84 | AC41: -2.31 | AD41: 1.71 | AE41: 45838 | AF41: 2.79 | AG41: -4.62 | AH41: 1.23 | AI41: 1.16 | AJ41: -1.96 | AK41: 1.38 | AL41: 45900 | AM41: 5.72 | AN41: -3.15 | AO41: 1.98 | AP41: 1.4 | AQ41: -1.69 | AR41: 1.44 | AS41: 45900 | AT41: 2.0937 | AU41: 45898 | AV41: 1.6608 | AW41: 1.6608 | AX41: 45898
A42: KWT | B42: iShares MSCI Kuwait ETF | C42: 44075 | D42: 0.74 | E42: 0.74 | F42: 84811303 | G42: 45909 | H42: Equity | I42: All Cap | J42: Kuwait | K42: Emerging | L42: Kuwait | M42: Index | N42: 3.3651 | O42: 45898 | P42: 24.671882 | Q42: 45909 | R42: 20.09 | S42: 25.97 | T42: 7.4 | U42: - | V42: - | W42: 14.38 | X42: 45838 | Y42: 20.27 | Z42: 26.11 | AA42: 7.03 | AB42: - | AC42: - | AD42: 14.32 | AE42: 45838 | AF42: 21.52 | AG42: 21.97 | AH42: 6.72 | AI42: - | AJ42: - | AK42: 14.13 | AL42: 45900 | AM42: 21.63 | AN42: 20.21 | AO42: 6.56 | AP42: - | AQ42: - | AR42: 14.06 | AS42: 45900 | AT42: 3.3651 | AU42: 45898 | AV42: 2.2633 | AW42: 2.2633 | AX42: 45898
A43: QAT | B43: iShares MSCI Qatar ETF | C43: 41758 | D43: 0.6 | E43: 0.6 | F43: 77613997 | G43: 45909 | H43: Equity | I43: All Cap | J43: Middle East and Africa | K43: Emerging | L43: Qatar | M43: Index | N43: 3.6304 | O43: 45898 | P43: 11.500972 | Q43: 45909 | R43: 5.93 | S43: 14.49 | T43: 0.49 | U43: 7.07 | V43: 1.77 | W43: 1.39 | X43: 45838 | Y43: 6.34 | Z43: 14.76 | AA43: 0.48 | AB43: 7.14 | AC43: 1.86 | AD43: 1.38 | AE43: 45838 | AF43: 12.81 | AG43: 17.26 | AH43: 0.04 | AI43: 6.38 | AJ43: 3.09 | AK43: 1.94 | AL43: 45900 | AM43: 14.23 | AN43: 18.02 | AO43: 0.23 | AP43: 6.68 | AQ43: 2.98 | AR43: 2 | AS43: 45900 | AT43: 3.6304 | AU43: 45898 | AV43: 3.8158 | AW43: 3.8158 | AX43: 45898
A44: ENZL | B44: iShares MSCI New Zealand ETF | C44: 40422 | D44: 0.5 | E44: 0.5 | F44: 74777529 | G44: 45909 | H44: Equity | I44: All Cap | J44: Asia Pacific | K44: Developed | L44: New Zealand | M44: Index | N44: 2.3282 | O44: 45898 | P44: 3.7135639 | Q44: 45909 | R44: 1.26 | S44: 3.31 | T44: 2.9 | U44: -1.83 | V44: 5.87 | W44: 7.89 | X44: 45838 | Y44: 1.91 | Z44: 2.64 | AA44: 3.08 | AB44: -2.06 | AC44: 5.85 | AD44: 7.89 | AE44: 45838 | AF44: 0.13 | AG44: -6.9 | AH44: 0.84 | AI44: -3.64 | AJ44: 6.53 | AK44: 7.72 | AL44: 45900 | AM44: 0.23 | AN44: -6.82 | AO44: 0.88 | AP44: -3.65 | AQ44: 6.46 | AR44: 7.67 | AS44: 45900 | AT44: 2.3282 | AU44: 45898 | AV44: 2.4178 | AW44: 2.4178 | AX44: 45898
A45: EIRL | B45: iShares MSCI Ireland ETF | C45: 40303 | D45: 0.5 | E45: 0.5 | F45: 60490846 | G45: 45909 | H45: Equity | I45: All Cap | J45: Europe | K45: Developed | L45: Broad | M45: Index | N45: 2.9448 | O45: 45869 | P45: 16.967885 | Q45: 45909 | R45: 16.98 | S45: 7.54 | T45: 20.69 | U45: 13.95 | V45: 7.2 | W45: 9.25 | X45: 45838 | Y45: 16.38 | Z45: 7.34 | AA45: 20.76 | AB45: 13.75 | AC45: 7.13 | AD45: 9.23 | AE45: 45838 | AF45: 16.967169 | AG45: -0.289434 | AH45: 18.865835 | AI45: 11.189196 | AJ45: 6.813004 | AK45: 9.147922 | AL45: 45900 | AM45: 16.81755 | AN45: -0.119312 | AO45: 18.910621 | AP45: 11.272266 | AQ45: 6.813612 | AR45: 9.147922 | AS45: 45900 | AT45: 2.9448 | AU45: 45869 | AV45: 2.196 | AW45: 2.196 | AX45: 45869
A46: ENOR | B46: iShares MSCI Norway ETF | C46: 40931 | D46: 0.53 | E46: 0.53 | F46: 41268894 | G46: 45909 | H46: Equity | I46: All Cap | J46: Europe | K46: Developed | L46: Norway | M46: Index | N46: 3.9245 | O46: 45898 | P46: 29.781004 | Q46: 45909 | R46: 27.45 | S46: 19.07 | T46: 9.24 | U46: 12.83 | V46: 5.39 | W46: 4.05 | X46: 45838 | Y46: 26.57 | Z46: 19.11 | AA46: 9.17 | AB46: 12.55 | AC46: 5.35 | AD46: 4.03 | AE46: 45838 | AF46: 29.6 | AG46: 19.4 | AH46: 8.25 | AI46: 9.28 | AJ46: 7.03 | AK46: 4.13 | AL46: 45900 | AM46: 28.48 | AN46: 18.82 | AO46: 8.29 | AP46: 9.35 | AQ46: 6.76 | AR46: 4.09 | AS46: 45900 | AT46: 3.9245 | AU46: 45898 | AV46: 3.9031 | AW46: 3.9031 | AX46: 45898
A47: EWK | B47: iShares MSCI Belgium ETF | C47: 35136 | D47: 0.5 | E47: 0.5 | F47: 35163849 | G47: 45909 | H47: Equity | I47: All Cap | J47: Europe | K47: Developed | L47: Belgium | M47: Index | N47: 2.1054 | O47: 45898 | P47: 27.687227 | Q47: 45909 | R47: 22.15 | S47: 23.29 | T47: 11.41 | U47: 8.91 | V47: 5.08 | W47: 5.45 | X47: 45838 | Y47: 22.06 | Z47: 22.61 | AA47: 11.38 | AB47: 8.82 | AC47: 5.02 | AD47: 5.42 | AE47: 45838 | AF47: 27.91 | AG47: 17.89 | AH47: 15.81 | AI47: 8.38 | AJ47: 5.77 | AK47: 5.58 | AL47: 45900 | AM47: 27.93 | AN47: 17.36 | AO47: 15.71 | AP47: 8.48 | AQ47: 5.77 | AR47: 5.56 | AS47: 45900 | AT47: 2.1054 | AU47: 45898 | AV47: 1.7859 | AW47: 1.7859 | AX47: 45898
A48: EFNL | B48: iShares MSCI Finland ETF | C48: 40933 | D48: 0.55 | E48: 0.55 | F48: 29849937 | G48: 45909 | H48: Equity | I48: All Cap | J48: Europe | K48: Developed | L48: Finland | M48: Index | N48: 4.4263 | O48: 45869 | P48: 36.312189 | Q48: 45909 | R48: 31.15 | S48: 22.4 | T48: 10.38 | U48: 7.43 | V48: 6.4 | W48: 7.6 | X48: 45838 | Y48: 30.66 | Z48: 22.13 | AA48: 10.39 | AB48: 7.29 | AC48: 6.37 | AD48: 7.59 | AE48: 45838 | AF48: 33.589957 | AG48: 17.80252 | AH48: 10.846945 | AI48: 4.624678 | AJ48: 6.964846 | AK48: 7.653668 | AL48: 45900 | AM48: 33.114086 | AN48: 17.371942 | AO48: 10.766745 | AP48: 4.530937 | AQ48: 6.918537 | AR48: 7.653668 | AS48: 45900 | AT48: 4.4263 | AU48: 45869 | AV48: 3.3182 | AW48: 3.3182 | AX48: 45869
A50: Please read full disclaimer below. To view disclaimer and definitions, double-click here. The performance quoted represents past performance and does not guarantee future results. Investment return and principal value of an investment will fluctuate so that an investor's shares, when sold or redeemed, may be worth more or less than the original cost. Current performance may be lower or higher than the performance quoted. Certain funds may have contractual or voluntary fee waivers that result in a Net Expense Ratio. For additional fee information, please click on the fund name above. This information must be preceded or accompanied by a current prospectus. Investors should read and consider it carefully before investing. To view a prospectus for an iShares ETF, please use the following link: https://www.ishares.com/us/library/financial-legal-tax. To view a prospectus for an iShares Index Mutual Fund, please use the following link: https://www.blackrock.com/us/individual/resources/regulatory-documents/mutual-funds Investing involves risk, including loss of principal. Shares of ETFs are bought and sold at market price (not NAV) and are not individually redeemed from the fund. Any applicable brokerage commissions will reduce returns. Beginning August 10, 2020, market price returns for BlackRock and iShares ETFs are calculated using the closing price and account for distributions from the fund. Prior to August 10, 2020, market price returns for BlackRock and iShares ETFs were calculated using the midpoint price and accounted for distributions from the fund. The midpoint is the average of the bid/ask prices at 4:00 PM ET (when NAV is normally determined for most ETFs). The returns shown do not represent the returns you would receive if you traded shares at other times. Performance shown may reflect fee waivers and/or expense reimbursements by the investment advisor to the fund for some or all of the periods shown. Performance would have been lower without such waivers. The iShares Funds are not sponsored, endorsed, issued, sold or promoted by Barclays, Bloomberg Finance L.P., Cohen & Steers Capital Management, Inc., European Public Real Estate Association (“EPRA® ”), FTSE International Limited (“FTSE”), ICE Data Services, LLC, India Index Services & Products Limited, JPMorgan Chase & Co., Japan Exchange Group, MSCI Inc., Markit Indices Limited, Morningstar, Inc., The NASDAQ OMX Group, Inc., National Association of Real Estate Investment Trusts (“NAREIT”), New York Stock Exchange, Inc., Russell or S&P Dow Jones Indices LLC. None of these companies make any representation regarding the advisability of investing in the Funds. BlackRock Investments, LLC is not affiliated with the companies listed above. Neither FTSE nor NAREIT makes any warranty regarding the FTSE NAREIT Equity REITS Index, FTSE NAREIT All Residential Capped Index or FTSE NAREIT All Mortgage Capped Index; all rights vest in NAREIT. Neither FTSE nor NAREIT makes any warranty regarding the FTSE EPRA/NAREIT Developed Real Estate ex-U.S. Index, FTSE EPRA/NAREIT Developed Europe Index or FTSE EPRA/NAREIT Global REIT Index; all rights vest in FTSE, NAREIT and EPRA.“FTSE®” is a trademark of London Stock Exchange Group companies and is used by FTSE under license. Certain information ©2020 MSCI ESG Research LLC. Reproduced by permission; no further distribution. Certain information contained herein (the “Information”) has been provided by MSCI ESG Research LLC, a RIA under the Investment Advisers Act of 1940, and may include data from its affiliates (including MSCI Inc. and its subsidiaries (“MSCI”)), or third party suppliers (each an “Information Provider”), and it may not be reproduced or redisseminated in whole or in part without prior written permission. The Information has not been submitted to, nor received approval from, the US SEC or any other regulatory body. The Information may not be used to create any derivative works, or in connection with, nor does it constitute, an offer to buy or sell, or a promotion or recommendation of, any security, financial instrument or product or trading strategy, nor should it be taken as an indication or guarantee of any future performance, analysis, forecast or prediction. Some funds may be based on or linked to MSCI indexes, and MSCI may be compensated based on the fund’s assets under management or other measures. MSCI has established an information barrier between equity index research and certain Information. None of the Information in and of itself can be used to determine which securities to buy or sell or when to buy or sell them. The Information is provided “as is” and the user of the Information assumes the entire risk of any use it may make or permit to be made of the Information. Neither MSCI ESG Research nor any Information Party makes any representations or express or implied warranties (which are expressly disclaimed), nor shall they incur liability for any errors or omissions in the Information, or for any damages related thereto. The foregoing shall not exclude or limit any liability that may not by applicable law be excluded or limited. © 2025 BlackRock, Inc or its affiliates. All Rights Reserved. BLACKROCK, iSHARES, iBONDS, LIFEPATH, ALADDIN and the iShares Core Graphic are trademarks of BlackRock, Inc. or its affiliates. All other trademarks are those of their respective owners. 12m Trailing Yield: The yield an investor would have received if they had held the fund over the last twelve months assuming the most recent NAV. The 12-Month yield is calculated by assuming any income distributions over the past twelve months and dividing by the sum of the most recent NAV and any capital gain distributions made over the past twelve months. 30-Day SEC Yield: A standard calculation of yield introduced by the SEC in order to provide fairer comparison among funds. This yield reflects the interest earned after deducting the fund's expenses during the most recent 30-day period by the average investor in the fund. Negative 30-Day SEC Yield results when accrued expenses of the past 30 days exceed the income collected during the past 30 days. Incept (%): For index mutual funds, since inception performance is included only for funds with less than ten years of performance history. For exchange-traded funds, since inception performance is always included. Unsubsidized 30-day Sec Yield (%) : Represents what a fund's 30-Day SEC Yield would have been had no fee waiver or expense reimbursement been in place over the period. Duration: Effective duration measures the sensitivity of the price of a bond with or without embedded options to changes in interest rates, taking into account the likelihood of the bond being called, put and/or sunk prior to its final maturity date while incorporating after-tax impacts on the bond. The options-based duration model used by BlackRock employs certain assumptions and may differ from other fund complexes. Effective Duration is measured at the individual bond level, aggregated to the portfolio level, and adjusted for leverage, hedging transactions and non-bond holdings, including derivatives. YTD Return (%): YTD (year to date) is a period, starting from the beginning of the current calendar year, and continuing up to the present day. Option Adjusted Spread : The weighted average incremental yield earned over similar duration US Treasuries, measured in basis points. This metric considers the likelihood that bonds will be called or prepaid before the scheduled maturity date. Avg Yield (%): Yield to Maturity is the discount rate that equates the present value of a bond's cash flows with its market price (including accrued interest). For callable bonds, this yield is the yield to worst. For TIPS, this yield includes the market's estimates for inflation over the life of the bond. The measure does not include fees and expenses. iCRMH0325U/S-4346190
